analyticsclient/__init__.py
analyticsclient/base.py
analyticsclient/client.py
analyticsclient/course.py
analyticsclient/course_summaries.py
analyticsclient/course_totals.py
analyticsclient/exceptions.py
analyticsclient/module.py
analyticsclient/programs.py
analyticsclient/status.py
analyticsclient/constants/__init__.py
analyticsclient/constants/activity_types.py
analyticsclient/constants/data_formats.py
analyticsclient/constants/demographics.py
analyticsclient/constants/education_levels.py
analyticsclient/constants/enrollment_modes.py
analyticsclient/constants/genders.py
analyticsclient/constants/http_methods.py
edx_analytics_data_api_client-0.18.3.dist-info/LICENSE.TXT
edx_analytics_data_api_client-0.18.3.dist-info/METADATA
edx_analytics_data_api_client-0.18.3.dist-info/NOTICE.TXT
edx_analytics_data_api_client-0.18.3.dist-info/WHEEL
edx_analytics_data_api_client-0.18.3.dist-info/top_level.txt
edx_analytics_data_api_client-0.18.3.dist-info/RECORD
