Metadata-Version: 2.1
Name: edx-analytics-data-api-client
Version: 0.18.3
Summary: Client used to access edX analytics data warehouse
Home-page: https://github.com/openedx/edx-analytics-data-api-client
Author: UNKNOWN
Author-email: UNKNOWN
License: Apache License 2.0
Platform: UNKNOWN
Classifier: Development Status :: 5 - Production/Stable
Classifier: Environment :: Web Environment
Classifier: Intended Audience :: Developers
Classifier: License :: OSI Approved :: Apache Software License
Classifier: Operating System :: OS Independent
Classifier: Programming Language :: Python
Classifier: Programming Language :: Python :: 3
Classifier: Programming Language :: Python :: 3.8
Requires-Dist: setuptools
Requires-Dist: requests
